[{"id":"UgyzfatmkIX6GiT2rSZ4AaABAg","parent":"root","text":"dopo averlo visto come minimo 20 volte ho deciso...questo va tra i preferiti XD\nPs:grazie di avermi fatto conoscere 331Erock,quel ragazzo é un grande XD","like_count":0,"author_id":"UCv5yw-TakxypT4FlUDJf3Hg","author":"@4ll4k4t4ll4","author_thumbnail":"https://yt3.ggpht.com/ytc/AIdro_lqZZRWVeH6XqGcG2ZzeqBwu4JEmbDI7YNnRMhtqBHk1FvxA0I=s88-c-k-c0x00ffffff-no-rj","author_is_uploader":false,"author_url":"https://www.youtube.com/@4ll4k4t4ll4","is_favorited":false,"timestamp":1398643200,"is_pinned":false},{"id":"UgzrAz-1GGkcAikvXL54AaABAg","parent":"root","text":"Ho una sola parola: delirante!","like_count":0,"author_id":"UCObvYdvpxncz9KBu7Cum_qw","author":"@96racco","author_thumbnail":"https://yt3.ggpht.com/ytc/AIdro_l-KeffmC59w4UxGYOfgJeMo8W3S7rV3ZnVo3PsQRE=s88-c-k-c0x00ffffff-no-rj","author_is_uploader":false,"author_url":"https://www.youtube.com/@96racco","is_favorited":false,"timestamp":1367107200,"is_pinned":false},{"id":"UgxuVB3DlxuH1jM4c3l4AaABAg","parent":"root","text":"Ci mancava il \"Ti devi spaventareeeeeeeeeeeeeeeeee!\" xD\n","like_count":0,"author_id":"UCUmxsKkm5_JQNJ3nwSH5t-g","author":"@Enigmixter","author_thumbnail":"https://yt3.ggpht.com/ytc/AIdro_nio4xCkNEdtBmY6M0m_6JKO08Czm30-meRuKR6fassxwk=s88-c-k-c0x00ffffff-no-rj","author_is_uploader":false,"author_url":"https://www.youtube.com/@Enigmixter","is_favorited":false,"timestamp":1367107200,"is_pinned":false},{"id":"UgzHYruTetl5aYmGGJV4AaABAg","parent":"root","text":"La canzone si chiama \"Skyrim Meets Metal\", di 331Erock (il link del suo canale lo trovi nella descrizione insieme al canale di Idiotcamel). ;)","like_count":0,"author_id":"UCSka2UHv1l4mMm1TUn00kcw","author":"@Youtubors","author_thumbnail":"https://yt3.ggpht.com/ytc/AIdro_lT21EXu0OTdxz1Fv4LIZGnREvT6WNIuGM649Xhx_aL=s88-c-k-c0x00ffffff-no-rj","author_is_uploader":true,"author_url":"https://www.youtube.com/@Youtubors","is_favorited":false,"timestamp":1367107200,"is_pinned":false},{"id":"UgxbRZvAzJHnJxuvaQl4AaABAg","parent":"root","text":"Ma come hai fatto la canzone di skyrim metal?","like_count":0,"author_id":"UCMVKgfj8NY1FBNC-JcgsAEw","author":"@MetalNick96","author_thumbnail":"https://yt3.ggpht.com/ytc/AIdro_nsmGQNMOPrgjJ0y1pBNhL2aQYS709_iNJVYk9R9uLx_g=s88-c-k-c0x00ffffff-no-rj","author_is_uploader":false,"author_url":"https://www.youtube.com/@MetalNick96","is_favorited":false,"timestamp":1367107200,"is_pinned":false},{"id":"Ugwj3YOl9uh1GGF9U5t4AaABAg","parent":"root","text":"la ringrazio del complimento! :)","like_count":0,"author_id":"UCSka2UHv1l4mMm1TUn00kcw","author":"@Youtubors","author_thumbnail":"https://yt3.ggpht.com/ytc/AIdro_lT21EXu0OTdxz1Fv4LIZGnREvT6WNIuGM649Xhx_aL=s88-c-k-c0x00ffffff-no-rj","author_is_uploader":true,"author_url":"https://www.youtube.com/@Youtubors","is_favorited":false,"timestamp":1367107200,"is_pinned":false},{"id":"Ugw10SqWcWaOioohBCl4AaABAg","parent":"root","text":"Assolutamente fantastica! :D","like_count":0,"author_id":"UCNJNajAM-zzRXfp0yQYebig","author":"@adefwrrea","author_thumbnail":"https://yt3.ggpht.com/ytc/AIdro_noroejx7QRmB5Y7f-miR8qFMYqWf8eVaPH3WI8Orgy72c=s88-c-k-c0x00ffffff-no-rj","author_is_uploader":false,"author_url":"https://www.youtube.com/@adefwrrea","is_favorited":false,"timestamp":1367107200,"is_pinned":false},{"id":"UgxhHYhZDCmy7LAjIld4AaABAg","parent":"root","text":"infatti non avevo intenzione di creare una ytpmv. è più un piccolissimo omaggio a idiotcamel!","like_count":0,"author_id":"UCSka2UHv1l4mMm1TUn00kcw","author":"@Youtubors","author_thumbnail":"https://yt3.ggpht.com/ytc/AIdro_lT21EXu0OTdxz1Fv4LIZGnREvT6WNIuGM649Xhx_aL=s88-c-k-c0x00ffffff-no-rj","author_is_uploader":true,"author_url":"https://www.youtube.com/@Youtubors","is_favorited":false,"timestamp":1367107200,"is_pinned":false}]