{"url":"https://www.youtube.com/watch?v=1xAEusIVdfI","title":"YTP ITA Collab : Disco Segreto poopato da Selfie","description":"I personaggi della famosa soap \" Il Segreto\" emettono strani versi a ritmo di canzoni da discoteca facendosi selfie !!\n\nBuona visione ! :)\n\nCollab tra :\n\nLukeMillennium92\nwww.youtube.com/channel/UC9mkmUOgcCyUVK3-k63dFbA\n\nAndrea97:\nwww.youtube.com/user/Andrea97channel\n\nCanzoni nel video:\nSkrillex- Bangrang\nKrewella-Alive\nThe Chainsmokers-#Selfie\n\nCanzone intro:\nIvan Gough & Feenixpawl ft Georgi Kay - In My Mind (Axwell Mix)","channel_name":"Andrea97_YTPs","channel_url":"https://www.youtube.com/@Andrea97YTPs","sections":["YTP fai da te"],"source_pages":["YTP fai da te\\68733940_COLLAB Andrea97 LukeMillennium92 YTP ITA Disco Segreto poopato da Selfie.html","channel_scrape:https://www.youtube.com/@Andrea97YTPs"],"status":"downloaded","local_file":"videos\\YTP fai da te\\YTP ITA Collab  Disco Segreto poopato da Selfie - 1xAEusIVdfI.mp4","publish_date":"2014-05-02","view_count":2704,"like_count":47,"nickname":"Andrea097","post_date":"4/5/2014, 21:18","language":"italian"}