{"url":"https://www.youtube.com/watch?v=1zaXC907Sd8","title":"Gux - Zelda CD-i experience","description":"This is a video set to the Zelda CD-i experience remix by Gux as found on Something Awful.\r\nThis didn't come out as I wanted, but I wanted to upload this by new years.\r\nGet this song, and all the other ones at.\r\nhttp://www.somethingawful.com/d/flash-tub/zelda-cdi-remix.php","channel_name":"ophios","channel_url":"https://www.youtube.com/@ophios","publish_date":"2007-01-01","view_count":128526,"like_count":1379,"tags":["MARLBORO","WALLACHIA","PENNE"],"status":"pending","language":"italian"}