{"url":"https://www.youtube.com/watch?v=3gWS16JVGz8","title":"YTP: National Pingas Radio","description":"I've never seen NPR used in a YouTube Poop, which is surprising given how many hours of transcribed, freely-downloadable audio they have.\n\nAlso please don't interpret any edits as my commentary on issues discussed in the source material (unless you agree with the commentary, in which case it's fine)\n\nSources:\n    • Fresh Air Nov. 3rd, 2021: Paul McCartney\n    • Up First Nov. 1st, 2021: UN Climate Summit\n    • Up First Oct 26th, 2021: Ex-Envoy On Afghanistan Exit\n    • The Indicator from Planet Money Oct 19th, 2021: Labor market trick or treat","channel_name":"TheChewanater","channel_url":"https://www.youtube.com/@TheChewanater","publish_date":"2021-11-04","view_count":5997,"like_count":497,"tags":[],"status":"pending"}