{"url":"https://www.youtube.com/watch?v=3H-3WwJPKYg","title":"Youtube Poop: Flyborg meets WEEGEE!!!!","description":"anyway, OMG, so reandug n funt!!!!, I LUB DA PERT WHEN..., and so on and so forth. \r\n\r\nI finally made a pop even with the block! HAHAHA!!! \r\n\r\nI make good youtube poops. YTPs because I put EFFORT INTO THEM!!!!","channel_name":"guysafari","channel_url":"https://www.youtube.com/@guysafari","publish_date":"2009-10-24","view_count":28965,"like_count":271,"tags":["FLYBORG","pokemon","zelda","toys","gone","wild","it's","over","9000","nine-thousand","deepercutt","walrusguy","hotel","mario","mama","luigi","RANDUMNESS!!!!!!!!!!!!!!!","the","wand","of","gamelon","faces","evil","link","king","impa","weegee","XDXD","gwonam","ganon","gannon","cd-i","shoop","da","whoop","spaghetti","TOASTAZ!?!?!?!","LOL!!!!","chad","warden","wardenn","chadwarden","KroboProductions","Krobo","Productions","pingas","XDXDXDXD","sonic","doctor","dr.","rabbit","dr.rabbit","billy","mays"],"status":"pending","language":"italian"}