{"url":"https://www.youtube.com/watch?v=_c3-1xv3NbA","title":"YTP ITA - Fantasmi e fighe inglesi","description":"ISCRIVITI: https://www.youtube.com/user/TheFilippoop\nFACEBOOK:https://www.facebook.com/Filippoop\nTWITTER: https://twitter.com/TheFilippoop\n\nLa visione di questo video è consigliata ad un pubblico adulto.\n\nTheFilippoop, Filippoop, The Filippoop, Youtube, Poop, Ita, YTP, YTP ITA, Youtube poop ita, Youtube merda, cacciatori di fantasmi, cacciatori di fantasmi stagione 5 ita, cacciatori di fantasmi dmax, cacciatori di fantasmi stagione 4 ita, cacciatori di fantasmi 2014, cacciatori di fantasmi ita, cacciatori di fantasmi stagione 5, cacciatori di fantasmi 2015, zak bagans, fantasmi, fantasmi veri video reali, YouTube Poop, ghost","channel_name":"TheFilippoop","channel_url":"https://www.youtube.com/@TheFilippoop","publish_date":"2014-03-22","view_count":33818,"like_count":615,"status":"downloaded","local_file":"videos\\TheFilippoop\\YTP ITA - Fantasmi e fighe inglesi - _c3-1xv3NbA.mkv","language":"italian"}