{"url":"https://www.youtube.com/watch?v=_v1zEw7c9lg","title":"THIS VIDEO DOESN'T CONTAIN GOURMET RACE","description":"FUCK MAN. I know.\r\nThis was my first musical fad, so the pitch is messed up a bit. But it's enjoyable I think. Plus, this is an old fad. Why are you people still watching this.\r\n\r\n\r\nEDIT: Oh look at thees, THE UNOFFICIAL MP3 made by MegaXalpha :0 http://www.megaupload.com/?d=XYUWMN60","channel_name":"Geogeo","channel_url":"https://www.youtube.com/@geogeobananarap","sections":["YTPMV dimportazione","YTP fai da te"],"source_pages":["YTPMV dimportazione\\33655720_THIS VIDEO DOESN'T CONTAIN GOURMET RACE.html","channel_scrape:https://www.youtube.com/@geogeobananarap","YTP fai da te\\42244494_mio primo poop\\page_1.html"],"status":"downloaded","local_file":"videos\\YTPMV dimportazione\\THIS VIDEO DOESN'T CONTAIN GOURMET RACE - _v1zEw7c9lg.mkv","publish_date":"2008-05-31","view_count":33143,"like_count":252,"nickname":"Morshu The Shopkeeper","post_date":"29/10/2008, 14:59","language":"italian"}