{"url":"https://www.youtube.com/watch?v=C7oba0h1HNU","title":"Generatore di canzoni di Domenico Bini (usa la tastiera)","description":"\"Nel 2020 le auto voleranno\"\n\nUsa i numeri della tastiera per comporre la tua personale canzone di Domenico Bini!\n\nLista delle frasi del maestro:\n| 0 |   Il Vulcano!\n| 1 |   Batman\n| 2 |   Dov'è finito Bruce Lee?\n| 3 |   Non sa più come fare!\n| 4 |   Finchè siamo in tempo, scappiamo via!\n| 5 |   Prepariamoci ad accoglierlo\n| 6 |   In the Massachusetts!\n| 7 |   E' andato in Giamaica! (Ooo)\n| 8 |   Che sarà, che sarà.. di lui!\n| 9 |   Nemico del mondo\n\n(NEI COMMENTI LA VERSIONE FUNZIONANTE DA MOBILE)\n\n• INSTAGRAM: https://www.instagram.com/poldo_ufficiale/\n• SHOP MAGLIETTE: https://www.slide24.com/poldo-akbar\n• LIVE: https://www.twitch.tv/poldolive\n• PAGINA FACEBOOK: https://www.facebook.com/mrpoldoakbar\n• SECONDO CANALE: https://goo.gl/novWBp\n\n---------------------------------------------------------\n\nYouTube è molto duro con il mio genere di video, eliminandomi la monetizzazione a quasi ogni video.\nSe hai voglia di vedere altri video del genere, e per aiutarmi a continuare a fare video, puoi valutare di donarmi una somma a tuo piacimento, anche solo per un pensiero.\nGrazie mille!\n\nhttps://ko-fi.com/mrpoldoakbar","channel_name":"MrPoldoAkbar ( ͡° ͜ʖ ͡°)","channel_url":"https://www.youtube.com/@mrpoldoakbar2849","publish_date":"2020-08-18","view_count":102598,"like_count":8912,"tags":["YTP ITA","Poldo","MrPoldoAkbar","WomboPoldo","Domenico","Domenico Bini","Bini","Il Vulcano","Shana Wana","Nico è andato in Giamaica","Domenico Bini canzoni","Domenico Bini divertente","Domenico Bini YTP"],"status":"pending","language":"italian"}