{"url":"https://www.youtube.com/watch?v=Cj8bb3AfI88","title":"YTP ita-il misterioso e perverso mulino","description":"woooo....secondo YTP di FCChanneltube commentate e iscrivetevi ;)","channel_name":"Lega Poop","channel_url":"https://www.youtube.com/@FCChannelTubePoop","sections":["YTP fai da te"],"source_pages":["YTP fai da te\\64628647_YTP ita-il misterioso e perverso mulino.html","channel_scrape:https://www.youtube.com/@FCChannelTubePoop"],"status":"downloaded","local_file":"videos\\YTP fai da te\\YTP ita-il misterioso e perverso mulino - Cj8bb3AfI88.mp4","publish_date":"2012-12-03","view_count":2232,"like_count":19,"nickname":"fcchannel","post_date":"15/1/2013, 16:24","language":"italian"}