{"url":"https://www.youtube.com/watch?v=HLuc-Sn2nsQ","title":"Una settimana di film p0rn0 (Entry Pubblicità Collab)","description":"Nella mia entry per la collab di Barsay si parla di una storia intrecciata e incomprensibile. Oltre a questo, si annuncia una bella settimana di film porno.\n\nCollab: https://youtu.be/LjLnba1PRO4?si=XcSurSXo8SlyUYFH","channel_name":"Tj8w","channel_url":"https://www.youtube.com/@Tj8w","publish_date":"2015-12-23","view_count":1549,"like_count":13,"tags":["Pokémon","YouTube Poop","Tj8w","Barsay","Le Pubblicità Fanno Sesso"],"status":"pending","language":"italian"}