{"url":"https://www.youtube.com/watch?v=QjcQ3-KsS18","title":"A Stairway to Mario's Eternity of 112 Wharks","description":"Round 4 of Audio-Only YTP Tennis: Strong414Bad vs. Me\r\n\r\nThe poor person m' Before competing in fact. Alida cos belong type myst of creative Russian. Qu' It my time l' In order from the data which is to Alida where creates from http://www.alidagame.com/ to be reunited in statics in because you this t or could seek and; ; Computer doesn' ; ; Mine? Program l' Is composing; magnetoscope registrations? T l' ; Approves many (odushevlennost) competitions and j' From [khwik] time, consequently; ; Pressure excess l' Should have become who; ; He will listen and the (thing) he originatesI'j'","channel_name":"MycroProcessor","channel_url":"https://www.youtube.com/@MycroProcessor","publish_date":"2008-11-02","view_count":805,"like_count":10,"tags":["alternative","blues","classical","country","electronic","folk","hip-hop","indie","jazz","pop","r&b","rap","religious","rock","soul","unsigned","world","music"],"status":"pending","language":"italian"}