{"url":"https://www.youtube.com/watch?v=RZPT6DmxSfM","title":"YTP: Da Grandi Poteri Derivano Grandi REDANOFER®","description":"Norman Osborn è osSESsionato dalle sue prestazioni S3Sualy e abuserà del SAS per ottenere questi risultati fino a ingoblinirsi. \nNel mentre un giovane evasore d'affitti viene a contatto con l'immenSooS potere del REDANOFER®, una sostanza distillata dalla MasterCast Co. dalla fusione di SAS e DNA di Richard Bensoos, ottenendo poteri infernalih per contenere situazioni disperate.\n\nPer chi non sapesse cosa sia il REDANOFER®: https://www.youtube.com/watch?v=dBosyzrkBuU\n--------------------------------------------------------------------------------------------------------------\n► TRACKLIST: \nTaking The Hobbits To Isengard (Remix)\nWindows Dance - DJ NikiforoV\nTommie Sunshine & KRUNK! - Bang Boom\nChapter Two (Original Mix) - Impulz & JMW\nAlex Gaudino - Destination Calabria (Justflow Remix)\nL'uomo puma - Volo\nDarude - Sandstorm\nBillie Benassi - Satisfaction Guy (ANGEMI vs. Rudeejay & Da Brozz Bootleg)\nYES - Roundabout \nGalwaro x B3nte - Violence (Original Mix)\nJoJo Bizarre Adventure Stardust Crusader OST - Dio's World\nDeadmau5 - Ghosts 'n Stuff [Instrumental Mix]\n--------------------------------------------------------------------------------------------------------------\nMerch & Social\n►►cAnale TWITCH: https://www.twitch.tv/giogio_cast\n►MAGLIETTAZIONE ONE SAS MAN: https://www.teezily.com/onesasman\n►MAGLIETTAZIONE MASTERCAST: https://www.moteefe.com/mastercastoriginal\n►SOSTIENI LE NUOVE VIDEAZIONI: https://www.youtube.com/watch?v=mnCF8ZPcF0I\n►INSTAGRAM: https://www.instagram.com/master.cast/\n►FACEBOOK: https://www.facebook.com/MasterCastPresident/\n►ARTICOLI STAM*NCHIA (feat.MasterCast, By teo_hp) : https://moteefe.com/mastercaststaminchia\n►DONAZIONI: https://streamlabs.com/giogio_cast","channel_name":"MasterCast","channel_url":"https://www.youtube.com/@MastercastPresident","publish_date":"2020-06-18","view_count":180554,"like_count":12581,"tags":["disney","marvel","sony","pezzali","883","uomo ragno","spiderman","goblin","benson","ita","SAS","vaiApagareLafietoAlPostoDiStarQuiSALAME"],"status":"pending","language":"italian"}