{"url":"https://www.youtube.com/watch?v=-j4kzOJF6xg","title":"AIDVISION: Hotel Mario","description":"As the title says. Pure aids from Hotel Mario","channel_name":"TheKooperPooper","channel_url":"https://www.youtube.com/@TheKooperPooper","publish_date":"2009-07-18","view_count":3585,"like_count":14,"tags":["aids","the","king","dinner","mah","boi","fad","gag","mama","luigi","cdi","invertion","ear","rape","video","trippy","acid","trip","m3l33","weed","pingas"],"status":"pending","language":"italian"}