{"url":"https://www.youtube.com/watch?v=7idm8-TRS5A","title":"YTP Tennis: Eddy Prefers Sanjaya to Boobies","description":"Round 2 of YTP Tennis vs. MahsuginaChicken.\r\n\r\nI realise that I am at a bit of a disadvantage, since I use WMM, which doesn't have as many effects as Adobe and Vegas.  But what I lack in effects I make up for in quality, and as you can see, I've got plenty of that.\r\n\r\nThere's also the fact that I'm facing a veteran in MahsuginaChicken, but if he shows any sign of hesitation, I WILL drop the dodongo on him! Enjoy! :)","channel_name":"Captpan6","channel_url":"https://www.youtube.com/@Captpan6","publish_date":"2007-12-25","view_count":17025,"like_count":90,"tags":["Tennis","YTPTennis","Ed","Edd","Eddy","Sanjaya","Quadruple","Kickflip","Captpan6","MahsuginaChicken"],"status":"pending","language":"italian"}