{"url":"https://www.youtube.com/watch?v=89z4qAZXRlY","title":"Youtube Poop: Sniff That!","description":"Berk sniffs something wicked in the kitchen and goes completely bonkers, spouting innuendo at his bonking friends whilst watching the castle light up like a christmas tree... well, a christmas tree that has sniffed the same stuff as Berk at least, whatever it was...","channel_name":"GreatBritishTurd","channel_url":"https://www.youtube.com/@GreatBritishTurd","publish_date":"2007-12-22","view_count":12480,"like_count":59,"tags":["Trapdoor","Trap","Door","Berk","sniff","british","80s","Claymation","bonk","bonking","weird","strange","awesome","awful"],"status":"pending","language":"italian"}