{"url":"https://www.youtube.com/watch?v=AczeT95ZjQQ","title":"{YTP} ~ Happy Mother Day!","description":"For Mother Day!\r\n\r\nDo I think mothers will watch this? ... No...\n\n\n\nSupport me: https://elliespectacular.com/support\n\nFAQ: https://elliespectacular.com/faq\n\nDaThings2: http://www.youtube.com/user/DaThings2","channel_name":"DaThings","channel_url":"https://www.youtube.com/@DaThings","publish_date":"2010-05-09","view_count":2439,"like_count":43,"tags":["youtube poop","mom","mothers day","day","your mother","your","spy"],"status":"pending","language":"english"}