{"url":"https://www.youtube.com/watch?v=Bs8wVCtLhGs","title":"Estate di Lil Angel$ ma è cantata dai Rhapsody of Fire","description":"\"Only one person could crossed the darklands sorrounding Ancona\nand venture forth deep into the caves of Fra-sassi...\nHis is a name the world will never forget...\nHe is Ben-J!\"\n🍷 Seguimi sul telegram https://t.me/nocoldiztv\n👉Link a tutti i miei social https://linktr.ee/nocoldiz\n🎥 e all'archivio segreto di Andreotti https://t.me/archiviodipaglia\n🐐 Gruppo ufficiale telegram: @lastalladipaglia","channel_name":"Nocoldiz","channel_url":"https://www.youtube.com/@nocoldizTV","publish_date":"2024-06-23","view_count":6879,"like_count":429,"tags":["rhapsody of fire","lil angels","nocoldiz","ai song"],"status":"pending","language":"italian"}