{"url":"https://www.youtube.com/watch?v=CxuhPidQQ_A","title":"YTPMV: How Metallica became famous","description":"Check it out.\r\n\r\nOriginal song:\r\nhttp://www.youtube.com/watch?v=65uNCLBTje0","channel_name":"CraaazyCat13","channel_url":"https://www.youtube.com/@CraaazyCat13","sections":["YTPMV dimportazione"],"source_pages":["YTPMV dimportazione\\40205921_YTPMV_ How Metallica became famous.html","YTPMV dimportazione\\40956308_Come i Metallica diventarono famosi.html","channel_scrape:https://www.youtube.com/@CraaazyCat13"],"status":"downloaded","local_file":"videos\\CraaazyCat13\\YTPMV How Metallica became famous - CxuhPidQQ_A.mkv","publish_date":"2009-06-09","view_count":65821,"like_count":1515,"nickname":"MamaTails","post_date":"10/6/2009, 21:01","language":"italian"}