{"url":"https://www.youtube.com/watch?v=IxbCDOxU6T4","title":"The Legend of Zelda: Oracle of Seasons/Ages - Maku Tree","description":"Music from TLoZ: OoS and OoA for the Game Boy Color. This track plays when talking to the Maku Tree.","channel_name":"Laizorb","channel_url":"https://www.youtube.com/@Laizorb","publish_date":"2008-04-19","view_count":2510,"like_count":18,"tags":["maku","tree","oos","ooa","music","theme","track","oracle","seasons","ages","link","baseball","is","boring"],"status":"downloaded","local_file":"videos\\Laizorb\\The Legend of Zelda Oracle of SeasonsAges - Maku Tree - IxbCDOxU6T4.mp4","language":"italian"}