{"url":"https://www.youtube.com/watch?v=JSCKr0-wTpE","title":"YTP: Lightning Eats Purina Ka-Chow","description":"In this video, Lightning and Mater skip the big race to crash some weddings.\n\nI've been working on this YouTube Poop on and off since 2022. Only this month did I have the chance to build it out the way I wanted, and by golly is it BEAUTIFUL!\n\n___________________________________________________\nIf you loved this, subscribe for more and if you want to support me on Patreon, do so here:\nhttps://www.patreon.com/Captpan6\n\nAnd you can also follow me on my socials for all sorts of other cool stuff!\nhttps://www.tiktok.com/@captpan\nhttps://bsky.app/profile/captpan6.bsky.social\n\n#ytp #youtubepoop","channel_name":"Captpan6","channel_url":"https://www.youtube.com/@Captpan6","publish_date":"2024-11-23","view_count":228800,"like_count":1968,"tags":["youtube poop","parody","cars","pixar","lightning","mcqueen","deez nuts","funny","comedy","remix","tow","mater","radiator","springs"],"status":"pending","language":"italian"}