{"url":"https://www.youtube.com/watch?v=L21pYGqWMKE","title":"[Micro - YTP] - Harky Breakdancing","description":"When you ask your father what if something happens to him but he tells you he'll take the Triforce of Courage to protect himself.\n\nCredits and Stuff:\n\n3D Models\n- King Harkinian (by Waxonator)\nhttps://www.youtube.com/watch?v=J3raUkNLV3A\n\n- Zelda (By C4DNerd)\nhttps://www.youtube.com/watch?v=U9KJlCKk6UA&t=37s\n\nMusic\nMisty vs Molly / Ralph Schuckett / Pokémon 3: The Movie - Spell of the Unown: Entei","channel_name":"SLBysusparidas","channel_url":"https://www.youtube.com/@SLBysusparidas","publish_date":"2022-07-16","view_count":772,"like_count":86,"status":"downloaded","local_file":"videos\\SLBysusparidas\\[Micro - YTP] - Harky Breakdancing - L21pYGqWMKE.mkv","language":"italian"}