{"url":"https://www.youtube.com/watch?v=M2tskI83V6g","title":"Zelda: Wand of Gamelon Intro (Original Dutch version) [RARE]","description":"Voice Cast: \r\n\r\nLink: Just Meijer \r\nZelda, Wizzrobe: Maria Lindes\r\nKing Harkinian/Ganon/Baker/Mayor Mayor Kravindish/Duke Onkled: Carol van Herwijnen \r\nImpa, Lady Alma, Cape woman in the forest: Beatrijs Sluijters\r\n\r\nEnglish subtitles now avalible.\r\n\r\nI finally got my hands on the dutch verion of Zelda: Wand of Gamelon. \r\n\r\nPlease rate, comment and enjoy.\r\n\r\nFeel free to use it in your poops.","channel_name":"kwarkman85","channel_url":"https://www.youtube.com/@kwarkman85","publish_date":"2008-09-29","view_count":34683,"like_count":363,"tags":["Zelda","Wand","of","Gamelon","Dutch","Faces","Evil"],"status":"pending","language":"italian"}