{"url":"https://www.youtube.com/watch?v=MN1Kvk0VAUM","title":"Tutti si uniscono alla Battaglia!","description":"Davvero, Stelio Kontos è il Captain Falcon che tutti desideriamo.\n\nVideo da cui ho preso parzialmente ispirazione: https://www.youtube.com/watch?v=TLPmOMmduS8\n\nTemplate (NON USATO DA ME):\nhttps://www.youtube.com/watch?v=5U5VyH6XQDw\n\n• MAGLIETTE: http://www.teezily.com/mrpoldoakbar\n• PAGINA FACEBOOK: https://www.facebook.com/mrpoldoakbar\n• GRUPPO TELEGRAM: https://t.me/mrpoldoakbargroup\n• CANALE TELEGRAM: https://t.me/mrpoldoakbartelegram\n• INSTAGRAM: https://www.instagram.com/poldo_ufficiale/","channel_name":"MrPoldoAkbar ( ͡° ͜ʖ ͡°)","channel_url":"https://www.youtube.com/@mrpoldoakbar2849","publish_date":"2018-09-03","view_count":1290631,"like_count":73334,"tags":["YTP ITA","Poldo","MrPoldoAkbar","Everyone Joins The Battle","Everyone Joins The Battle Meme","Everyone Joins The Battle Smash","Everyone Joins The Battle Italia","Everyone Joins The Battle ita","Super Smash Bros","Smash","Smash meme","Super Smash Bros Meme","Super Smash Bros. Ultimate"],"status":"pending","language":"italian"}