{"url":"https://www.youtube.com/watch?v=StKx5ZCYl7g","title":"[S01E04] Dab nei campetti da calcio e Mussolini a corde","description":"Ecco il trailer di Death No-ob-the!\n\nEcco la trilogia delle iPoop Channel:\nATTO PRIMO: https://www.youtube.com/watch?v=UfYzJqfJK9Y\nATTO SECONDO: https://www.youtube.com/watch?v=AkAT6WHFITs\nATTO TERZO: https://www.youtube.com/watch?v=lQmuBKBr_NM\n\nScusatemi, ripeto che in questo periodo sono senza ispirazione.\nMa tranquilli, questi momenti passano! (Spero!)\n\n• INSTAGRAM: https://www.instagram.com/poldo_ufficiale/\n\nNext: ?","channel_name":"MrPoldoAkbar ( ͡° ͜ʖ ͡°)","channel_url":"https://www.youtube.com/@mrpoldoakbar2849","publish_date":"2016-10-18","view_count":257605,"like_count":11721,"tags":["Youtube Merda","YTP ITA","Poldo","MrPoldoAkbar","iNoobchannel","iNoobchannel MrPoldoAkbar","iNoobchannel ytp","inoobchannel ytp ita"],"status":"pending","language":"italian"}