{"url":"https://www.youtube.com/watch?v=SYK8rDqcRts","title":"YTP ITA - Obscurio è diventato WOKE e de sinistra???","description":"Dopo il primo contatto con l'energia Neozon, Obscurio ha improvvisamente evoluto il suo GENDER in conformazioni frattali che non possiamo neanche immaginare, nel frattempo all'inferno stanno organizzando una grande parata di benvenuto per Ozzy.\n🍷 Seguimi sul telegram https://t.me/nocoldiztv\n👉Link a tutti i miei social https://linktr.ee/nocoldiz\n🎥 e all'archivio segreto di Andreotti https://t.me/archiviodipaglia\n🐐 Gruppo ufficiale telegram: @lastalladipaglia","channel_name":"Nocoldiz","channel_url":"https://www.youtube.com/@nocoldizTV","publish_date":"2025-07-24","view_count":16764,"like_count":2124,"tags":["nocoldiz","superman woke","dario moccia","james gun","superman","lgbt","gormito","obscurio","matt gallus"],"status":"pending","language":"italian"}