[{"id":"Ugh3b9_ULJCGWngCoAEC","parent":"root","text":"Come ha detto scusi? Illi!risosii! 😂","like_count":0,"author_id":"UCNO9G_UaXp0t2TSfbF10fYQ","author":"@oldsnake93100","author_thumbnail":"https://yt3.ggpht.com/oSZeBpXyF_Wi7j3OtHQQyf5SKSrsHE7n2Gkw0LMiGVawIy7WgK668p1Ah3MyatxJvbX1FvJl=s88-c-k-c0x00ffffff-no-rj","author_is_uploader":false,"author_url":"https://www.youtube.com/@oldsnake93100","is_favorited":false,"timestamp":1493337600,"is_pinned":false},{"id":"UgxG47B3vCqUgHQ8OF94AaABAg","parent":"root","text":"AHAHHAAHHAAHHAHAHAHAHHAHHAAAHAH","like_count":0,"author_id":"UC9bxebHZtXBVJgGsJvoBouw","author":"@callimacoafidna4597","author_thumbnail":"https://yt3.ggpht.com/ytc/AIdro_mbTDeqsY6iIm3cofTX_ZS-ehjo_2pG-W1qDWeQqZM=s88-c-k-c0x00ffffff-no-rj","author_is_uploader":false,"author_url":"https://www.youtube.com/@callimacoafidna4597","is_favorited":false,"timestamp":1367107200,"is_pinned":false},{"id":"UgwtctFVaChOkv1ekz54AaABAg","parent":"root","text":"Grazie, uso Sony Vegas.\nSu YouTube trovi diversi tutorial su come creare Poop, ce n'è uno di Nocoldiz che è fatto molto bene. (:","like_count":0,"author_id":"UC9sLle_ANzwwhsaci_lNexQ","author":"@CrazyPooper","author_thumbnail":"https://yt3.ggpht.com/ytc/AIdro_nx6vtx6O2d57MlX2JEoclqB14TTM5s41r1l9dt8kZbog=s88-c-k-c0x00ffffff-no-rj","author_is_uploader":true,"author_url":"https://www.youtube.com/@CrazyPooper","is_favorited":false,"timestamp":1367107200,"is_pinned":false},{"id":"Ugx-xxY1NKgFfNJQzRx4AaABAg","parent":"root","text":"bello ma che programma usi'????????","like_count":0,"author_id":"UCLWtpMF9KQhDqa9-wRuBA2A","author":"@fserlenga90","author_thumbnail":"https://yt3.ggpht.com/ytc/AIdro_m5CNrqhalZklPU2YvuuOGM37cPSo3bdBErl9Hhm6k7Ew=s88-c-k-c0x00ffffff-no-rj","author_is_uploader":false,"author_url":"https://www.youtube.com/@fserlenga90","is_favorited":false,"timestamp":1367107200,"is_pinned":false}]