[{"id":"UgxaKsOWnnafJM7_8z14AaABAg","parent":"root","text":"Senza barba sembra scemo più scemo","like_count":0,"author_id":"UC8f7q1rckoVNtKm3O6l1HEA","author":"@TrollMalefico1984","author_thumbnail":"https://yt3.ggpht.com/ytc/AIdro_lPdambIPD3Afa2p6Ie8CySkMNaAeD9zA82d2eJCig8KA=s88-c-k-c0x00ffffff-no-rj","author_is_uploader":false,"author_url":"https://www.youtube.com/@TrollMalefico1984","is_favorited":false,"timestamp":1769558400,"is_pinned":false},{"id":"UgjYswehKzUUVngCoAEC","parent":"root","text":"Canzone a 6:57?","like_count":1,"author_id":"UCmuNuc6Yc8Zzb30G1eYf_nQ","author":"@TestohZuppa","author_thumbnail":"https://yt3.ggpht.com/ytc/AIdro_kZDQJg3OTY0RBnV2zZ_Dvs12aSqSozZRqHniSAxaWX0w=s88-c-k-c0x00ffffff-no-rj","author_is_uploader":false,"author_url":"https://www.youtube.com/@TestohZuppa","is_favorited":false,"timestamp":1461801600,"is_pinned":false},{"id":"Ugi1lo6H-RGCWHgCoAEC","parent":"root","text":"MI AVETE FATTO SCHIATTARE!! AHAAHHA","like_count":0,"author_id":"UCl0ho5ORcrCK5pExrGfyy_A","author":"@VortexNovaOfficialTube","author_thumbnail":"https://yt3.ggpht.com/ytc/AIdro_kRmuz7CllMcaZRN7K30TAweHMeajO2_wRlVm_etPmr3ajm=s88-c-k-c0x00ffffff-no-rj","author_is_uploader":false,"author_url":"https://www.youtube.com/@VortexNovaOfficialTube","is_favorited":false,"timestamp":1461801600,"is_pinned":false},{"id":"UgjV5k9prM6ewngCoAEC","parent":"root","text":"6:12 come si chiama la canzone????","like_count":0,"author_id":"UC0LpcAQ9ye_GRkGmGM65_JQ","author":"@davide5712","author_thumbnail":"https://yt3.ggpht.com/ytc/AIdro_k2p_1fwDDG6LKmaQx2wwqhWd48JFF86sDLmudzlnIzKas=s88-c-k-c0x00ffffff-no-rj","author_is_uploader":false,"author_url":"https://www.youtube.com/@davide5712","is_favorited":false,"timestamp":1430179200,"is_pinned":false},{"id":"UgjV5k9prM6ewngCoAEC.7-H0Z7-8EWo70Aa9roE-RP","parent":"UgjV5k9prM6ewngCoAEC","text":"Knife Party - Centipede","like_count":0,"author_id":"UC6OvMVpYECNS-gyT8pIqivQ","author":"@Daniele231195","author_thumbnail":"https://yt3.ggpht.com/ytc/AIdro_l2ryBDvSa8gdwFtr1SbkeJzl75bKelgwBcD1Ln9hlI7A=s88-c-k-c0x00ffffff-no-rj","author_is_uploader":false,"author_url":"https://www.youtube.com/@Daniele231195","is_favorited":false,"timestamp":1430179200,"is_pinned":false},{"id":"UghIycCgJsxhoHgCoAEC","parent":"root","text":"La miglior poop che abbia mai visto.","like_count":0,"author_id":"UCEt1Mr5Vi8OLCBi7f9wKvrg","author":"@user-my2mr4co5w","author_thumbnail":"https://yt3.ggpht.com/ytc/AIdro_nKNjrXuJxWcWIMnvtIqHE2eA51nJbKwCQ9oGiYWaqmzz0=s88-c-k-c0x00ffffff-no-rj","author_is_uploader":false,"author_url":"https://www.youtube.com/@user-my2mr4co5w","is_favorited":false,"timestamp":1430179200,"is_pinned":false},{"id":"UggXHPlrUvZ7m3gCoAEC","parent":"root","text":"A 3:44 collasserete XD\nGiuro sono morto","like_count":0,"author_id":"UCqCY_O8j46Vq0q23LgGaXFg","author":"@Gioco190","author_thumbnail":"https://yt3.ggpht.com/ytc/AIdro_kCmsAsvLVrrNIw3f5wdpDzztWi3d_xdgFxFxBYxOZKIp3D=s88-c-k-c0x00ffffff-no-rj","author_is_uploader":false,"author_url":"https://www.youtube.com/@Gioco190","is_favorited":false,"timestamp":1430179200,"is_pinned":false},{"id":"UgjxtuNtgyP5uXgCoAEC","parent":"root","text":"5:32 lai preso da howtobasic evvero?","like_count":0,"author_id":"UC7IuHkfLRCpHokqwtkbHnsw","author":"@LucaITWarrock","author_thumbnail":"https://yt3.ggpht.com/ytc/AIdro_k3Ae7B6gNB6asoGXmL49ayoCuVhHpasjt41u8UmYNNcuk=s88-c-k-c0x00ffffff-no-rj","author_is_uploader":false,"author_url":"https://www.youtube.com/@LucaITWarrock","is_favorited":false,"timestamp":1430179200,"is_pinned":false},{"id":"UggRAmsiQRIR33gCoAEC","parent":"root","text":"Ma a 0:27 è Lucy In The Sky with Diamonds!","like_count":0,"author_id":"UC0imuQsh7jmnMf8o2CZjXWg","author":"@BigBossXCV","author_thumbnail":"https://yt3.ggpht.com/ytc/AIdro_mpNu9ZIRdzm_m_qDshuflONwZ2NL6xwAKV1Dug2q26vzw=s88-c-k-c0x00ffffff-no-rj","author_is_uploader":false,"author_url":"https://www.youtube.com/@BigBossXCV","is_favorited":false,"timestamp":1430179200,"is_pinned":false},{"id":"UggRAmsiQRIR33gCoAEC.7-H0Z7-78iK8ke-QPHWPQF","parent":"UggRAmsiQRIR33gCoAEC","text":"Esatto","like_count":0,"author_id":"UC-Rfj2GV8arv97cCaOwV4EQ","author":"@Brokenface","author_thumbnail":"https://yt3.ggpht.com/ZY0XvaroRWZjB5nCuMDRlQJdTtfe75Y8Y5ZpURU_LhzEvmf9lu1xZthbeTG-N7zXcFCA80u8TA=s88-c-k-c0x00ffffff-no-rj","author_is_uploader":false,"author_url":"https://www.youtube.com/@Brokenface","is_favorited":false,"timestamp":1556409600,"is_pinned":false},{"id":"UggiuaAPE1PjCXgCoAEC","parent":"root","text":"Cotto & Frullato Maurizio Merluzzo Look at this","like_count":0,"author_id":"UC0imuQsh7jmnMf8o2CZjXWg","author":"@BigBossXCV","author_thumbnail":"https://yt3.ggpht.com/ytc/AIdro_mpNu9ZIRdzm_m_qDshuflONwZ2NL6xwAKV1Dug2q26vzw=s88-c-k-c0x00ffffff-no-rj","author_is_uploader":false,"author_url":"https://www.youtube.com/@BigBossXCV","is_favorited":false,"timestamp":1430179200,"is_pinned":false},{"id":"UghzY5KDPORWeHgCoAEC","parent":"root","text":"Un mi piace per il Kebabbaro di fiducia!","like_count":3,"author_id":"UCLcSj5E_Ts45j77WB5CZA4Q","author":"@Valerio_Bellic","author_thumbnail":"https://yt3.ggpht.com/ytc/AIdro_lzDMP8BgwuH0LcUkzLRdkWIhQsqszt3b00Ijd6fSI2iSA=s88-c-k-c0x00ffffff-no-rj","author_is_uploader":false,"author_url":"https://www.youtube.com/@Valerio_Bellic","is_favorited":false,"timestamp":1430179200,"is_pinned":false},{"id":"Ugi2PrD1JJf1i3gCoAEC","parent":"root","text":"Gnacca was here","like_count":0,"author_id":"UC6j3vfeqTGrd13JgaWPgYmg","author":"@bathman5700","author_thumbnail":"https://yt3.ggpht.com/ytc/AIdro_nqzDo43GWWTkJTIQ4PyVnyao5jVcI1v4ZMW5_VY8L4hLk=s88-c-k-c0x00ffffff-no-rj","author_is_uploader":false,"author_url":"https://www.youtube.com/@bathman5700","is_favorited":false,"timestamp":1430179200,"is_pinned":false},{"id":"Ugh3fxGrECWNjHgCoAEC","parent":"root","text":"Homessomipiacepersbagliononsuccederàpiùnonuccidermi","like_count":0,"author_id":"UC_3_n2WLaFhRnmA_g-2vvSA","author":"@DOGcity99","author_thumbnail":"https://yt3.ggpht.com/Kd0dG-sISLI7L-LFfRGMj6H4kcBt5tcycCp9K2_DEF0RG8ftgHNUs41bpS4BlkluL2bw-km6sNA=s88-c-k-c0x00ffffff-no-rj","author_is_uploader":false,"author_url":"https://www.youtube.com/@DOGcity99","is_favorited":false,"timestamp":1430179200,"is_pinned":false},{"id":"UgjR9tUQD-drhXgCoAEC","parent":"root","text":"1:48 come si chiama la cansoncina\n\n\nricordo perché in un episodio dei simpson homer cantava c'era una piccola pulcetin...ecc XD","like_count":0,"author_id":"UCbYOUPDVq4ZCkYoLt7Ps7QA","author":"@JosephPBD","author_thumbnail":"https://yt3.ggpht.com/ytc/AIdro_kl6enVVTA8y86ZgcmC012KLp9niDwB_7IVCxrXyQQ1yA=s88-c-k-c0x00ffffff-no-rj","author_is_uploader":false,"author_url":"https://www.youtube.com/@JosephPBD","is_favorited":false,"timestamp":1430179200,"is_pinned":false},{"id":"UgiVCyzQqHq71XgCoAEC","parent":"root","text":"DROP THAT FRULLATO!","like_count":0,"author_id":"UCWFGfxuDv72s3LG15WidMfg","author":"@TheIlBarco","author_thumbnail":"https://yt3.ggpht.com/ytc/AIdro_kqF8ax7gl5xXVHspOBghl31ME3SMLmTj6VUC_-dEQCwCw=s88-c-k-c0x00ffffff-no-rj","author_is_uploader":false,"author_url":"https://www.youtube.com/@TheIlBarco","is_favorited":false,"timestamp":1430179200,"is_pinned":false},{"id":"UgiLTfh4-A1bpXgCoAEC","parent":"root","text":"6:11 EPICITAAAAAAA!!","like_count":0,"author_id":"UCB5y7XhZcOkytyV_7alIWaA","author":"@Kyroro97","author_thumbnail":"https://yt3.ggpht.com/hNFsYoLc--etYxmpAy7bGHP2xo5pVmqwVYWq4l4pEPsDjudE1bihUE8rYLcdjPbE6Ti5XWfaGQ=s88-c-k-c0x00ffffff-no-rj","author_is_uploader":false,"author_url":"https://www.youtube.com/@Kyroro97","is_favorited":false,"timestamp":1398643200,"is_pinned":false},{"id":"UgiMDS7tyYv0NngCoAEC","parent":"root","text":"Perché puppato è meglio! AHAHAHAHAHAHAH che descrizione 😂😂😂😂","like_count":2,"author_id":"UCXxLt8InfboAbMPZ0JX3FDw","author":"@federico6740","author_thumbnail":"https://yt3.ggpht.com/ytc/AIdro_ld3S6oXwAFitmkwv1eZptZqt7juTC836Z0N9dXwWt_lfi2=s88-c-k-c0x00ffffff-no-rj","author_is_uploader":false,"author_url":"https://www.youtube.com/@federico6740","is_favorited":false,"timestamp":1398643200,"is_pinned":false},{"id":"Ugg92XGXYmKWUXgCoAEC","parent":"root","text":"7:28","like_count":0,"author_id":"UC5Isjrl4WhOmT3Z7XWBtccg","author":"@Ophiocordyses","author_thumbnail":"https://yt3.ggpht.com/ytc/AIdro_k6nhnh-z0qOb1prmuQdsGOB9eQxDvZaXmEXY842Z7x7ybQ=s88-c-k-c0x00ffffff-no-rj","author_is_uploader":false,"author_url":"https://www.youtube.com/@Ophiocordyses","is_favorited":false,"timestamp":1398643200,"is_pinned":false},{"id":"UghIggKxaCNvFngCoAEC","parent":"root","text":"Nuovo iscritto bellissimo video!","like_count":0,"author_id":"UCbdH9SS-EW2e1eT2BqQEfyQ","author":"@richardbenson5701","author_thumbnail":"https://yt3.ggpht.com/ytc/AIdro_kUV28hQWGH4q27z9mMn4p6-aGuZHzDVmStCOjGml1ekQ=s88-c-k-c0x00ffffff-no-rj","author_is_uploader":false,"author_url":"https://www.youtube.com/@richardbenson5701","is_favorited":false,"timestamp":1398643200,"is_pinned":false},{"id":"UgiZHC8ZnaI-kXgCoAEC","parent":"root","text":"OMMIODDIO È UN TERRORISTAH","like_count":0,"author_id":"UC7caAeR4eu7_jl-e5H1PfbA","author":"@assassinosoldato92","author_thumbnail":"https://yt3.ggpht.com/ytc/AIdro_mZ8SsdLZtuh5JLv1YGXtuD-EyaiJCe_2f34u6W4QRebg=s88-c-k-c0x00ffffff-no-rj","author_is_uploader":false,"author_url":"https://www.youtube.com/@assassinosoldato92","is_favorited":false,"timestamp":1398643200,"is_pinned":false},{"id":"UggRAfHY7n37x3gCoAEC","parent":"root","text":"lucy in the sky with diamonds al posto dell'harlem shake: TI VOGLIO BENE!! <3","like_count":2,"author_id":"UCJXhJf4RkNWosEj8hrpLbkQ","author":"@cinefactsit","author_thumbnail":"https://yt3.ggpht.com/AVGLBXmVsO-R4sR0wsmtIUqK07ViD22xGfRwceyMalJdXIV-dLyVM3LCY8SbQ3b02SOKq_ZiEyA=s88-c-k-c0x00ffffff-no-rj","author_is_uploader":false,"author_url":"https://www.youtube.com/@cinefactsit","is_favorited":false,"timestamp":1398643200,"is_pinned":false},{"id":"UgiBeO5qCEaDjHgCoAEC","parent":"root","text":"Non vedevo una poop così bella e geniale da tanto tempo","like_count":0,"author_id":"UCYdwv3hwSw9t6J52nbx39dQ","author":"@DaniloTestoh4","author_thumbnail":"https://yt3.ggpht.com/ytc/AIdro_mQ0D6qS9NVrj19_TDO6F_FAib-Fc5xCBHIVfGyfdUD1RI=s88-c-k-c0x00ffffff-no-rj","author_is_uploader":false,"author_url":"https://www.youtube.com/@DaniloTestoh4","is_favorited":false,"timestamp":1398643200,"is_pinned":false},{"id":"Ugi-Gxgoh1CICHgCoAEC","parent":"root","text":"Bella, ma la battuta sul kebabbaro di fiducia era telefonata xD","like_count":0,"author_id":"UC0ZRXlqXWZHT7xWc2gxZeYA","author":"@gordoneuomolibero363","author_thumbnail":"https://yt3.ggpht.com/ytc/AIdro_lhOycqVfIXd-3ZAEZDy14-UkYgWDoMkcTgjLxEqpfGCg=s88-c-k-c0x00ffffff-no-rj","author_is_uploader":false,"author_url":"https://www.youtube.com/@gordoneuomolibero363","is_favorited":false,"timestamp":1398643200,"is_pinned":false},{"id":"Ughkmthr_4Djp3gCoAEC","parent":"root","text":"Magnifica collab!","like_count":0,"author_id":"UCbtX3mhAKCpsOVz3Pi-DULw","author":"@TheLoller3000","author_thumbnail":"https://yt3.ggpht.com/ytc/AIdro_mtpA6xnHCYiN-dmABugey9CZsaTEJ4ipR4kafmrQg=s88-c-k-c0x00ffffff-no-rj","author_is_uploader":false,"author_url":"https://www.youtube.com/@TheLoller3000","is_favorited":false,"timestamp":1398643200,"is_pinned":false},{"id":"UghXABqNgIMTq3gCoAEC","parent":"root","text":"COCAINA! Big up per solvo e per dan mentre piwut é lezzo","like_count":0,"author_id":"UCY0CgepdVvBZBQxqI-aD3GQ","author":"@dagosma1","author_thumbnail":"https://yt3.ggpht.com/ytc/AIdro_kF_3lZ97gZHY7-PIHWjkFWourzoXt6E1QWluq8d8cm7A=s88-c-k-c0x00ffffff-no-rj","author_is_uploader":false,"author_url":"https://www.youtube.com/@dagosma1","is_favorited":false,"timestamp":1398643200,"is_pinned":false},{"id":"UgiDdRgPDDEcd3gCoAEC","parent":"root","text":"si prende il pene CON LE MANI......","like_count":0,"author_id":"UC32bxa8LSkYU5CbwfSZ-MrA","author":"@BustyPigeon00","author_thumbnail":"https://yt3.ggpht.com/T-PO7rFqg9YA-4ZFN5PtHMhM350sOfB48JKvZqQmSI01dEEkkF7JQ2WXdG0fBZev7oE_EsRW=s88-c-k-c0x00ffffff-no-rj","author_is_uploader":false,"author_url":"https://www.youtube.com/@BustyPigeon00","is_favorited":false,"timestamp":1398643200,"is_pinned":false},{"id":"Ugg9uULm6fXzjngCoAEC","parent":"root","text":"6:33","like_count":0,"author_id":"UCiy9jtRHHz6SyA4KCI_RR2w","author":"@TheDastanMr","author_thumbnail":"https://yt3.ggpht.com/ytc/AIdro_mIr-eytGgPMgrc69_HrzJA3EipCLYfdIHLognY7e_mzg=s88-c-k-c0x00ffffff-no-rj","author_is_uploader":false,"author_url":"https://www.youtube.com/@TheDastanMr","is_favorited":false,"timestamp":1398643200,"is_pinned":false},{"id":"UghU6hOLTcO_7ngCoAEC","parent":"root","text":"oddio jack black è un tocco di classe\npeccato che in italia pochi la capiranno ","like_count":0,"author_id":"UC0Rgi2cWgSLr9b3tXYwB10A","author":"@hdman511","author_thumbnail":"https://yt3.ggpht.com/ytc/AIdro_maNKNJyS0qrUmk9RtJZ8hHa7M0Yc9_yc4Kfer6ErI=s88-c-k-c0x00ffffff-no-rj","author_is_uploader":false,"author_url":"https://www.youtube.com/@hdman511","is_favorited":false,"timestamp":1398643200,"is_pinned":false},{"id":"UgiH4txDfOSfdngCoAEC","parent":"root","text":"Hahahaha xD","like_count":3,"author_id":"UCqlOeVVDBdDCvMM5JvB5p4g","author":"@travisscotti","author_thumbnail":"https://yt3.ggpht.com/7uzcSyiOK0rN-z_uOrGCBHlQ6ocFhBM2LvwJDbjL9kigML7v5_AGY5b7pBfTn7WCBfAZb_9s=s88-c-k-c0x00ffffff-no-rj","author_is_uploader":false,"author_url":"https://www.youtube.com/@travisscotti","is_favorited":false,"timestamp":1398643200,"is_pinned":false},{"id":"UgjYZMv3KSdeAHgCoAEC","parent":"root","text":"a 5:51 sono MORTO! AHAHAHAHAHAHAHA Bellissima Poop!","like_count":2,"author_id":"UCoTGTEWD97ghEQ5X46a-3wA","author":"@polianskee","author_thumbnail":"https://yt3.ggpht.com/ytc/AIdro_l8yBceRg4vfGK2OOESlXZCGurp4nfc3u5UkLeC1YZiTkw=s88-c-k-c0x00ffffff-no-rj","author_is_uploader":false,"author_url":"https://www.youtube.com/@polianskee","is_favorited":false,"timestamp":1398643200,"is_pinned":false},{"id":"UggXMkeILZv70XgCoAEC","parent":"root","text":"TELE AGRAAAAS <3","like_count":0,"author_id":"UC1_8R0Pm3xTiYax5Rg53SNA","author":"@bartopanzer","author_thumbnail":"https://yt3.ggpht.com/0Bz93yNNLnn-8Og-jH89CaSC3XUCK_M_gjfuOpjOJ1CvKasp75gPHNn7X8vPfPPcQWZlwm-nEA=s88-c-k-c0x00ffffff-no-rj","author_is_uploader":false,"author_url":"https://www.youtube.com/@bartopanzer","is_favorited":false,"timestamp":1398643200,"is_pinned":false},{"id":"UggSqv9FLXUp1XgCoAEC","parent":"root","text":"il capo dei lavori","like_count":0,"author_id":"UCkOQmirQNPfkCY41gU8ck-Q","author":"@anploader4134","author_thumbnail":"https://yt3.ggpht.com/ytc/AIdro_kUpHI9f2ezUOAbxjp5yB18f17sb5Ns3ayGG8bNLUlQKt4=s88-c-k-c0x00ffffff-no-rj","author_is_uploader":false,"author_url":"https://www.youtube.com/@anploader4134","is_favorited":false,"timestamp":1398643200,"is_pinned":false},{"id":"UgheidV9GvR9wHgCoAEC","parent":"root","text":"Fantastica Poop!!! Il signore oscuro (io) approva questa Poop XD.","like_count":1,"author_id":"UC4ZGeppTUD8T2O9QENU9ZPA","author":"@darthfenerita","author_thumbnail":"https://yt3.ggpht.com/ytc/AIdro_l2-t9SwuuQ5EUVvhL-i2JPqvg_mIa0hsKOE20jlpudx-0=s88-c-k-c0x00ffffff-no-rj","author_is_uploader":false,"author_url":"https://www.youtube.com/@darthfenerita","is_favorited":false,"timestamp":1398643200,"is_pinned":false},{"id":"UggqUIETIyGMiHgCoAEC","parent":"root","text":"4:12 hahahahhahahhhahahaha","like_count":1,"author_id":"UC7pOsSw6FVA-MzsTaEX1bNQ","author":"@bearingintoexistance","author_thumbnail":"https://yt3.ggpht.com/ytc/AIdro_nVDi860a6KTJdWn3q36N6OSaYZ94hImO6iymQEv9WbSYM=s88-c-k-c0x00ffffff-no-rj","author_is_uploader":false,"author_url":"https://www.youtube.com/@bearingintoexistance","is_favorited":false,"timestamp":1398643200,"is_pinned":false},{"id":"UgjkjZn-fck053gCoAEC","parent":"root","text":"Non respiro!!","like_count":0,"author_id":"UC0imuQsh7jmnMf8o2CZjXWg","author":"@BigBossXCV","author_thumbnail":"https://yt3.ggpht.com/ytc/AIdro_mpNu9ZIRdzm_m_qDshuflONwZ2NL6xwAKV1Dug2q26vzw=s88-c-k-c0x00ffffff-no-rj","author_is_uploader":false,"author_url":"https://www.youtube.com/@BigBossXCV","is_favorited":false,"timestamp":1398643200,"is_pinned":false},{"id":"UgjxsbIOv2j1J3gCoAEC","parent":"root","text":"sei un genio quando hai messo i beatles =D","like_count":0,"author_id":"UCoi_FcuRFGieCih2-4kQ2hQ","author":"@gianlucacraft33","author_thumbnail":"https://yt3.ggpht.com/ytc/AIdro_ml9svoEjwGl2_BdSC3xXAxAydIUVHBI0ha9EKsCM6jBQ=s88-c-k-c0x00ffffff-no-rj","author_is_uploader":false,"author_url":"https://www.youtube.com/@gianlucacraft33","is_favorited":false,"timestamp":1398643200,"is_pinned":false},{"id":"UgiSDbw0eAiDUHgCoAEC","parent":"root","text":"AHAHHAHAAAHAHAHAHAHHAHA ODDIO DARIO KEBABBARO E' QUALCOSA DI UNICO HAHAHA ODDIO ","like_count":0,"author_id":"UCV5uCPgeLshtYUf_S_DNDKA","author":"@puffolo98","author_thumbnail":"https://yt3.ggpht.com/ytc/AIdro_neXXU5gylNaD-4xXfsgCpXzVWbVqqEDRwHLo-xisVQdw=s88-c-k-c0x00ffffff-no-rj","author_is_uploader":false,"author_url":"https://www.youtube.com/@puffolo98","is_favorited":false,"timestamp":1398643200,"is_pinned":false},{"id":"UgiWSelVvrp5pXgCoAEC","parent":"root","text":"vi AMO!","like_count":0,"author_id":"UCpVv_izzfxTayk5oJxBvp-w","author":"@DaviRed95","author_thumbnail":"https://yt3.ggpht.com/ytc/AIdro_lPJmSet5hW6LpFBfJ33uXau9BwvmsStlYuKTDCGX2DlXA=s88-c-k-c0x00ffffff-no-rj","author_is_uploader":false,"author_url":"https://www.youtube.com/@DaviRed95","is_favorited":false,"timestamp":1398643200,"is_pinned":false},{"id":"UgieNJBGVdaIxngCoAEC","parent":"root","text":"L'ultima parte è di un altro video che si chiama Risotto Reflection","like_count":0,"author_id":"UCdfSS8BrQVIlEXYoBRmqWuw","author":"@zwair42069","author_thumbnail":"https://yt3.ggpht.com/ytc/AIdro_lQzoE8FOeI-T3FnQLlfUYKfqJpOcqPIa1nvmO5ujt4AUc=s88-c-k-c0x00ffffff-no-rj","author_is_uploader":false,"author_url":"https://www.youtube.com/@zwair42069","is_favorited":false,"timestamp":1398643200,"is_pinned":false},{"id":"UgjBHQiGqfDX83gCoAEC","parent":"root","text":"Sò sbregà in dò dae risate! ahahah xD","like_count":0,"author_id":"UCyhY34HWBRNLgsGPKAPQ_Eg","author":"@95krive","author_thumbnail":"https://yt3.ggpht.com/ytc/AIdro_kMKIRXUZ9mMVHvlJZ9yUhBvOO5m142oiIH2REcUBMsVg=s88-c-k-c0x00ffffff-no-rj","author_is_uploader":false,"author_url":"https://www.youtube.com/@95krive","is_favorited":false,"timestamp":1398643200,"is_pinned":false},{"id":"UghgFIZbZCTCF3gCoAEC","parent":"root","text":"favoloso!","like_count":0,"author_id":"UC6QTkWj0UQOXMfyhgS-pkRA","author":"@OldHarryMTX","author_thumbnail":"https://yt3.ggpht.com/ytc/AIdro_mY0b9cMjPz447lQHCzvyTI5f2MzYy7_avzIfrYyQqdJQ=s88-c-k-c0x00ffffff-no-rj","author_is_uploader":false,"author_url":"https://www.youtube.com/@OldHarryMTX","is_favorited":false,"timestamp":1398643200,"is_pinned":false},{"id":"Ugie4CBLO3Jkw3gCoAEC","parent":"root","text":"Complimenti atttuuuutti, nuovo colpo del cannoneviaaaaa, ma qual è la parte di Danthoriu esattamente? dopo un po avete rimosso gli avatar e non ho più capito","like_count":8,"author_id":"UCk6EQK4a-w35_i6SghQyp7w","author":"@TheFelixxxmaster","author_thumbnail":"https://yt3.ggpht.com/ytc/AIdro_nz5LQKkqD8OCE1C1R1cH9U6bKamEJtqffetjhk3H68upM=s88-c-k-c0x00ffffff-no-rj","author_is_uploader":false,"author_url":"https://www.youtube.com/@TheFelixxxmaster","is_favorited":false,"timestamp":1398643200,"is_pinned":false},{"id":"Ugie4CBLO3Jkw3gCoAEC.7-H0Z7-672h7-I_MJ5UX3e","parent":"Ugie4CBLO3Jkw3gCoAEC","text":"A 4:30 comincia la parte di Dan.","like_count":0,"author_id":"UC4rC8eLr9mQJo56aiUc09SQ","author":"@EvilYorkiz","author_thumbnail":"https://yt3.ggpht.com/9zB4UVo1xjWS67C9HFJ4PVGtKKefqsO1802OqfTRAiH1bHql__L_HYYkgBjX4c6cMIi9dWdx=s88-c-k-c0x00ffffff-no-rj","author_is_uploader":true,"author_url":"https://www.youtube.com/@EvilYorkiz","is_favorited":false,"timestamp":1398643200,"is_pinned":false},{"id":"UggRxQvb_TIHOngCoAEC","parent":"root","text":"Sei un folle ❤️","like_count":0,"author_id":"UC3mR_reITR7Bhiyz6FuwxTQ","author":"@Giovanniygo","author_thumbnail":"https://yt3.ggpht.com/wDD4jbJuyvBX6sh4ZfGgezuey5CYig3yfplrAEbINDAGct7ZZqtKuxb3Vsop_C8O99VGpkFX=s88-c-k-c0x00ffffff-no-rj","author_is_uploader":false,"author_url":"https://www.youtube.com/@Giovanniygo","is_favorited":false,"timestamp":1398643200,"is_pinned":false},{"id":"UghndGTIgj-h6HgCoAEC","parent":"root","text":"Prese il Guanabana, lo spezzò e disse \"Io ho il pene enorme, e voi no\" \nSTIMA INFINITA","like_count":4,"author_id":"UCWH8j8S9IQrqGDUdfTWFlTg","author":"@Blazor67","author_thumbnail":"https://yt3.ggpht.com/izdfwhn6S-r-F2jgDlTW_FjTBkDxvtIeJ9TenfSy7OdcNAtNvM1my-eVBrfnFBqJ6IeL-OB0=s88-c-k-c0x00ffffff-no-rj","author_is_uploader":false,"author_url":"https://www.youtube.com/@Blazor67","is_favorited":false,"timestamp":1398643200,"is_pinned":false},{"id":"UgiCAiWx3zffSXgCoAEC","parent":"root","text":"Cazzo ma è fantastico!\nsono morto a \"tu pensa a girare\"","like_count":34,"author_id":"UC9zrKSo7Es5pHfBMaH4Vq-w","author":"@idiotcamel","author_thumbnail":"https://yt3.ggpht.com/wGDnYI0ZNqjWWp8bBq1mFpvwCVw6PcfhCiurFyhrp31ZxxMov472G6-gMR6tVVqlsTVKvBW0Eg=s88-c-k-c0x00ffffff-no-rj","author_is_uploader":false,"author_url":"https://www.youtube.com/@idiotcamel","is_favorited":false,"timestamp":1398643200,"is_pinned":false},{"id":"Ught10vgZWW2QngCoAEC","parent":"root","text":"Il merluzzo alla fine me l'aspettavo.","like_count":0,"author_id":"UCT5TA-tyQNaxJ1fDk_f1fIA","author":"@KrockodileReborn","author_thumbnail":"https://yt3.ggpht.com/ytc/AIdro_lQKXRNxJkT4x_FN22Joqqr5eY5Uh8X1TdHmXeYd3WzHg=s88-c-k-c0x00ffffff-no-rj","author_is_uploader":false,"author_url":"https://www.youtube.com/@KrockodileReborn","is_favorited":false,"timestamp":1398643200,"is_pinned":false},{"id":"UggiBEj6Rge33HgCoAEC","parent":"root","text":"bravissimi, bel collab!","like_count":4,"author_id":"UC-fD_qwTEQQ1L-MUWx_mNvg","author":"@revergo","author_thumbnail":"https://yt3.ggpht.com/ytc/AIdro_mXM2QXWX6hMi31asEBZMdrp-1L-CI4cVEcuOb53HVPMw=s88-c-k-c0x00ffffff-no-rj","author_is_uploader":false,"author_url":"https://www.youtube.com/@revergo","is_favorited":false,"timestamp":1398643200,"is_pinned":false},{"id":"UggN_HpjigMu83gCoAEC","parent":"root","text":"Adesso chiamerò il mio Kebbabbaro di Fiducia!.... Chiama Dario Moccia Azzeccatissimo!","like_count":10,"author_id":"UC5M2Qyop4QEXpKveO0xn4-g","author":"@TagFul19","author_thumbnail":"https://yt3.ggpht.com/mFQVEICyMNR-P0mrRARLBQMGBT93_dI3j2CtthTj4qiG6MY75uqdErKMjAP4uO1Av1--LRdBLw=s88-c-k-c0x00ffffff-no-rj","author_is_uploader":false,"author_url":"https://www.youtube.com/@TagFul19","is_favorited":false,"timestamp":1398643200,"is_pinned":false},{"id":"UgjF8w7ivvkty3gCoAEC","parent":"root","text":"0:52 a meno che non sia una cosa plagiata, mi sembra dei Rhapsody of Fire..","like_count":0,"author_id":"UC2HRH_jjOyK4S0MUn7kM4qw","author":"@Busta","author_thumbnail":"https://yt3.ggpht.com/ytc/AIdro_mSsesEbA3bPN_umK48S2uWLAfJAI1W8dpo-LKZ6Y6F53c=s88-c-k-c0x00ffffff-no-rj","author_is_uploader":false,"author_url":"https://www.youtube.com/@Busta","is_favorited":false,"timestamp":1398643200,"is_pinned":false},{"id":"UgjF8w7ivvkty3gCoAEC.7-H0Z7-2Frk7-Hjnrt9ady","parent":"UgjF8w7ivvkty3gCoAEC","text":"Sì esatto, l'ho resa più \"satanica\"!","like_count":0,"author_id":"UC4rC8eLr9mQJo56aiUc09SQ","author":"@EvilYorkiz","author_thumbnail":"https://yt3.ggpht.com/9zB4UVo1xjWS67C9HFJ4PVGtKKefqsO1802OqfTRAiH1bHql__L_HYYkgBjX4c6cMIi9dWdx=s88-c-k-c0x00ffffff-no-rj","author_is_uploader":true,"author_url":"https://www.youtube.com/@EvilYorkiz","is_favorited":false,"timestamp":1398643200,"is_pinned":false},{"id":"UgjF8w7ivvkty3gCoAEC.7-H0Z7-2Frk7-HktqevYqp","parent":"UgjF8w7ivvkty3gCoAEC.7-H0Z7-2Frk7-Hjnrt9ady","text":"Ho un udito sopraffino, eheh","like_count":0,"author_id":"UC2HRH_jjOyK4S0MUn7kM4qw","author":"@Busta","author_thumbnail":"https://yt3.ggpht.com/ytc/AIdro_mSsesEbA3bPN_umK48S2uWLAfJAI1W8dpo-LKZ6Y6F53c=s88-c-k-c0x00ffffff-no-rj","author_is_uploader":false,"author_url":"https://www.youtube.com/@Busta","is_favorited":false,"timestamp":1398643200,"is_pinned":false},{"id":"UgjF8w7ivvkty3gCoAEC.7-H0Z7-2Frk7-HlLS0x44i","parent":"UgjF8w7ivvkty3gCoAEC.7-H0Z7-2Frk7-HktqevYqp","text":"Vabè dai si capisce, poi l'ho dovuta modificare anche per la storia del copyright...","like_count":0,"author_id":"UC4rC8eLr9mQJo56aiUc09SQ","author":"@EvilYorkiz","author_thumbnail":"https://yt3.ggpht.com/9zB4UVo1xjWS67C9HFJ4PVGtKKefqsO1802OqfTRAiH1bHql__L_HYYkgBjX4c6cMIi9dWdx=s88-c-k-c0x00ffffff-no-rj","author_is_uploader":true,"author_url":"https://www.youtube.com/@EvilYorkiz","is_favorited":false,"timestamp":1398643200,"is_pinned":false},{"id":"UgjF8w7ivvkty3gCoAEC.7-H0Z7-2Frk7-Hl_9fQhl6","parent":"UgjF8w7ivvkty3gCoAEC.7-H0Z7-2Frk7-HktqevYqp","text":"Sì, è vero, poi dipende quanta gente li conosca, e quanti conoscono proprio quell'album. Infatti al primo ascolto mi sono detto \"l'ho già sentita, cazzo\".\nComunque, bel lavoro!","like_count":0,"author_id":"UC2HRH_jjOyK4S0MUn7kM4qw","author":"@Busta","author_thumbnail":"https://yt3.ggpht.com/ytc/AIdro_mSsesEbA3bPN_umK48S2uWLAfJAI1W8dpo-LKZ6Y6F53c=s88-c-k-c0x00ffffff-no-rj","author_is_uploader":false,"author_url":"https://www.youtube.com/@Busta","is_favorited":false,"timestamp":1398643200,"is_pinned":false},{"id":"UgjF8w7ivvkty3gCoAEC.7-H0Z7-2Frk7-HnUuXcy8X","parent":"UgjF8w7ivvkty3gCoAEC.7-H0Z7-2Frk7-HktqevYqp","text":"Grazie!","like_count":0,"author_id":"UC4rC8eLr9mQJo56aiUc09SQ","author":"@EvilYorkiz","author_thumbnail":"https://yt3.ggpht.com/9zB4UVo1xjWS67C9HFJ4PVGtKKefqsO1802OqfTRAiH1bHql__L_HYYkgBjX4c6cMIi9dWdx=s88-c-k-c0x00ffffff-no-rj","author_is_uploader":true,"author_url":"https://www.youtube.com/@EvilYorkiz","is_favorited":false,"timestamp":1398643200,"is_pinned":false},{"id":"Ugj4BoctBere03gCoAEC","parent":"root","text":"dopo secoli...ECCOLO","like_count":2,"author_id":"UCUd_SUjVA5E783nYwPe3cVg","author":"@Nint3ndoleggend","author_thumbnail":"https://yt3.ggpht.com/ytc/AIdro_lce5-BOKheePDHYbnbgo1xZBXiUWBcNvdd9nLyn2t9GiU=s88-c-k-c0x00ffffff-no-rj","author_is_uploader":false,"author_url":"https://www.youtube.com/@Nint3ndoleggend","is_favorited":false,"timestamp":1398643200,"is_pinned":false},{"id":"UggqLWTjCyCvVHgCoAEC","parent":"root","text":"in fottuto capolavoro! :D","like_count":0,"author_id":"UCIe25bLbW8zFjL6m4TTJGqQ","author":"@danielescovolo4719","author_thumbnail":"https://yt3.ggpht.com/ytc/AIdro_mKOWHdMm_2UJxFUEDkNPrqBAURxIqnQv8FJ041WQROFwM=s88-c-k-c0x00ffffff-no-rj","author_is_uploader":false,"author_url":"https://www.youtube.com/@danielescovolo4719","is_favorited":false,"timestamp":1398643200,"is_pinned":false},{"id":"UgiS2trBJmCzb3gCoAEC","parent":"root","text":"Non vedo l'ora ahahah","like_count":0,"author_id":"UCN8pQ9l0NiUZ2JhMAhds26A","author":"@giammyzanna","author_thumbnail":"https://yt3.ggpht.com/gNb6l1tO8m4LcmsGQZSEG6mDBUfRlK9ngS95gIZog_8bkuWmnfI4CI-razxAbuKWfNrklXQDluQ=s88-c-k-c0x00ffffff-no-rj","author_is_uploader":false,"author_url":"https://www.youtube.com/@giammyzanna","is_favorited":false,"timestamp":1398643200,"is_pinned":false},{"id":"UgiyWgdrFggJEHgCoAEC","parent":"root","text":"Maurizio Merluzzo ","like_count":0,"author_id":"UContKg4i4AXW8onhkmMYmxg","author":"@luc1s","author_thumbnail":"https://yt3.ggpht.com/ytc/AIdro_lI27BYvfVF4b3J00u7HQznbOCAWIFGLR8pZzYtTaeyE5o=s88-c-k-c0x00ffffff-no-rj","author_is_uploader":false,"author_url":"https://www.youtube.com/@luc1s","is_favorited":false,"timestamp":1398643200,"is_pinned":false},{"id":"UgjvPRAHZTjD03gCoAEC","parent":"root","text":"Ah ammettilo Evil: quel ''Lol'' al minuto 3:53 è un tributo alla mia magnifica magnificenza vero? xD","like_count":0,"author_id":"UCAc2W14NDFvYZyMvK_fAu5g","author":"@LolFunDoppiaggi","author_thumbnail":"https://yt3.ggpht.com/Y0gEt6bYz3QpirjQd22zwlt7FH5Kojhm7XqME_-bffY0M8sXYExQ3w67p0D6OJnat_Kku8Hm=s88-c-k-c0x00ffffff-no-rj","author_is_uploader":false,"author_url":"https://www.youtube.com/@LolFunDoppiaggi","is_favorited":false,"timestamp":1398643200,"is_pinned":false},{"id":"UgjvPRAHZTjD03gCoAEC.7-H0Z7-9kIJ7-II3jxvm-x","parent":"UgjvPRAHZTjD03gCoAEC","text":"Beh ovvio <3","like_count":0,"author_id":"UC4rC8eLr9mQJo56aiUc09SQ","author":"@EvilYorkiz","author_thumbnail":"https://yt3.ggpht.com/9zB4UVo1xjWS67C9HFJ4PVGtKKefqsO1802OqfTRAiH1bHql__L_HYYkgBjX4c6cMIi9dWdx=s88-c-k-c0x00ffffff-no-rj","author_is_uploader":true,"author_url":"https://www.youtube.com/@EvilYorkiz","is_favorited":false,"timestamp":1398643200,"is_pinned":false},{"id":"UgiqQVhZosD39HgCoAEC","parent":"root","text":"ahahahah la parte con Dario Moccia mi ha fatto morire","like_count":0,"author_id":"UCxih_vX_4zGbrRCazwbfE-A","author":"@DiegoM193","author_thumbnail":"https://yt3.ggpht.com/ytc/AIdro_mySoB7qHNP0A1uHXXoHQZsUE1cyyZxjIX8mrO3G8nDnw=s88-c-k-c0x00ffffff-no-rj","author_is_uploader":false,"author_url":"https://www.youtube.com/@DiegoM193","is_favorited":false,"timestamp":1398643200,"is_pinned":false},{"id":"UgiMm2hyj9bBa3gCoAEC","parent":"root","text":"Geniale, veramente geniale complimenti\n10/10","like_count":5,"author_id":"UCZ1RhVeC8qJmNuPENLpMRVw","author":"@LaTavernaDelleMinchiate","author_thumbnail":"https://yt3.ggpht.com/-daVEe9pbWo9SEV35ZhXXA90OJ0BKrccZXVdNzPZzucri58B3083UX17JTfkZB7oTQDwB0iq7d4=s88-c-k-c0x00ffffff-no-rj","author_is_uploader":false,"author_url":"https://www.youtube.com/@LaTavernaDelleMinchiate","is_favorited":false,"timestamp":1398643200,"is_pinned":false},{"id":"UggaCVFc56EUmngCoAEC","parent":"root","text":"Questa poop è un capolavoro: la migliore parte era o quella del kebbabaro oppure quella del risotto ai funghi (anzichè con le erbette)!","like_count":0,"author_id":"UCRf70SpMMrdPoZI1HaIOMKQ","author":"@MakotoJupiterX","author_thumbnail":"https://yt3.ggpht.com/1DUz7Ud1pk7cwurpTnNNXUxZK0NppKCJf6l8sX7I-8W3mOdVm_gLDckB4VxYwcP1xUZ3XgQtPg=s88-c-k-c0x00ffffff-no-rj","author_is_uploader":false,"author_url":"https://www.youtube.com/@MakotoJupiterX","is_favorited":false,"timestamp":1398643200,"is_pinned":false},{"id":"UghGYiRTDiTI-HgCoAEC","parent":"root","text":" 8:09 troppo epicità in un solo momento","like_count":0,"author_id":"UCSE-d7wnAaGoxoVR84-z3dA","author":"@ThePowahGamer","author_thumbnail":"https://yt3.ggpht.com/ytc/AIdro_mt3AfDp7d9A5GYL_Mg94FGyG7mETxBKH4Edh7ROoXU7w=s88-c-k-c0x00ffffff-no-rj","author_is_uploader":false,"author_url":"https://www.youtube.com/@ThePowahGamer","is_favorited":false,"timestamp":1398643200,"is_pinned":false},{"id":"Ugg3zNE-TS6YUXgCoAEC","parent":"root","text":"Deve marinare per nino 666","like_count":0,"author_id":"UCpf0Ey3GZLipZwkWVmfAQrQ","author":"@loockmartin","author_thumbnail":"https://yt3.ggpht.com/ytc/AIdro_lSzuhDn4y1qFsPZ9maOzltPP5-ZpI3jPhgN4rR9-s=s88-c-k-c0x00ffffff-no-rj","author_is_uploader":false,"author_url":"https://www.youtube.com/@loockmartin","is_favorited":false,"timestamp":1398643200,"is_pinned":false},{"id":"UgjOA6ANRB1sfXgCoAEC","parent":"root","text":"Fiero di aver \"lavorato\" con voi.\nE' venuto qualcosa di formidabile! Grazie a tutti","like_count":36,"author_id":"UClGar-YfeZVXaUmderGBYkw","author":"@DanThoRiu","author_thumbnail":"https://yt3.ggpht.com/ytc/AIdro_lIsRy3zXJo2dD1WR95xgffnEp-3Gn1bxrwENCWbTYGXO0=s88-c-k-c0x00ffffff-no-rj","author_is_uploader":false,"author_url":"https://www.youtube.com/@DanThoRiu","is_favorited":false,"timestamp":1398643200,"is_pinned":false},{"id":"UgjOA6ANRB1sfXgCoAEC.7-H0Z7-ORJW7-H0qohcz2q","parent":"UgjOA6ANRB1sfXgCoAEC","text":"Grazie a te! ","like_count":14,"author_id":"UC4rC8eLr9mQJo56aiUc09SQ","author":"@EvilYorkiz","author_thumbnail":"https://yt3.ggpht.com/9zB4UVo1xjWS67C9HFJ4PVGtKKefqsO1802OqfTRAiH1bHql__L_HYYkgBjX4c6cMIi9dWdx=s88-c-k-c0x00ffffff-no-rj","author_is_uploader":true,"author_url":"https://www.youtube.com/@EvilYorkiz","is_favorited":false,"timestamp":1398643200,"is_pinned":false},{"id":"UgjOA6ANRB1sfXgCoAEC.7-H0Z7-ORJW73-0RC65zm9","parent":"UgjOA6ANRB1sfXgCoAEC","text":"EvilYorkiz ***** SolvoPoops \nComplimenti per il collab! =)","like_count":2,"author_id":"UCdsvy72hgtPeAI6NRZB7BYQ","author":"@harrysimonthebest","author_thumbnail":"https://yt3.ggpht.com/ytc/AIdro_nil2hBXREpwrXZgc5foGqrhVe5kDNpH6omP6TlXsLXKA=s88-c-k-c0x00ffffff-no-rj","author_is_uploader":false,"author_url":"https://www.youtube.com/@harrysimonthebest","is_favorited":false,"timestamp":1430179200,"is_pinned":false},{"id":"UgjOA6ANRB1sfXgCoAEC.7-H0Z7-ORJW7E-TEz4sjOP","parent":"UgjOA6ANRB1sfXgCoAEC","text":"popo fieroh!","like_count":0,"author_id":"UChJhixsMxNOrVCIEe1-NrlA","author":"@riukeyaghamy1285","author_thumbnail":"https://yt3.ggpht.com/ytc/AIdro_l55H1U5xzs0M8_cNYF4qnPc1IOs80modp8qhOE7GfNug=s88-c-k-c0x00ffffff-no-rj","author_is_uploader":false,"author_url":"https://www.youtube.com/@riukeyaghamy1285","is_favorited":false,"timestamp":1430179200,"is_pinned":false},{"id":"UghjvWzI-aQUJHgCoAEC","parent":"root","text":"Grandi ragazzi, un collab da morir dal ridere! non riesco a citare una sola parte che faccia sganasciare di più, siete stati bravissimi! Ora non me ne vogliate, vado a prendere il respiratore, sapete mi manca l'aria :D ","like_count":3,"author_id":"UCAc2W14NDFvYZyMvK_fAu5g","author":"@LolFunDoppiaggi","author_thumbnail":"https://yt3.ggpht.com/Y0gEt6bYz3QpirjQd22zwlt7FH5Kojhm7XqME_-bffY0M8sXYExQ3w67p0D6OJnat_Kku8Hm=s88-c-k-c0x00ffffff-no-rj","author_is_uploader":false,"author_url":"https://www.youtube.com/@LolFunDoppiaggi","is_favorited":false,"timestamp":1398643200,"is_pinned":false},{"id":"UgjacmgzScwE2HgCoAEC","parent":"root","text":"KKKEEEEBBBBBAAAAAAAABBBBBBB","like_count":0,"author_id":"UCfAbBj3Fdeu7S5lyYZ0qxSQ","author":"@RiccardOGmain","author_thumbnail":"https://yt3.ggpht.com/ytc/AIdro_mTCsvJj0aJ23rgMYxtpZnl-BkoL7qzaNdQlHfEbvJF7kE=s88-c-k-c0x00ffffff-no-rj","author_is_uploader":false,"author_url":"https://www.youtube.com/@RiccardOGmain","is_favorited":false,"timestamp":1398643200,"is_pinned":false},{"id":"Ugj1HFYa3uOgo3gCoAEC","parent":"root","text":"Mi sono emozionato","like_count":1,"author_id":"UCoVfgNxmffbQ522-D4ivSFQ","author":"@OurTube1011","author_thumbnail":"https://yt3.ggpht.com/-YVJ7NHrDdBLAE7_u-9caD_fxN4y-l1K9HUe_iCJDVl3p1dsTtC22QkNQUMhwf63TrU9nOc72g=s88-c-k-c0x00ffffff-no-rj","author_is_uploader":false,"author_url":"https://www.youtube.com/@OurTube1011","is_favorited":false,"timestamp":1398643200,"is_pinned":false},{"id":"UgjP8UjXUhNRgngCoAEC","parent":"root","text":"AHAHAHAHHAHAH","like_count":0,"author_id":"UCvsjHXmOFg0qc2Mdr4a8FFA","author":"@Saimo23","author_thumbnail":"https://yt3.ggpht.com/ytc/AIdro_kJN1_nlgnw0zxtCPBhTo2DQYdN5DygNrVUmUAAaCe8EsM=s88-c-k-c0x00ffffff-no-rj","author_is_uploader":false,"author_url":"https://www.youtube.com/@Saimo23","is_favorited":false,"timestamp":1398643200,"is_pinned":false},{"id":"UghoO2xNeP6kRHgCoAEC","parent":"root","text":"6:11 puoi dirmi la canzone, è la stessa di scolopendra","like_count":0,"author_id":"UCRhNVyj8Aqtx7K6qUwi5wsQ","author":"@RedHotCivyPepper","author_thumbnail":"https://yt3.ggpht.com/ytc/AIdro_mHDCGjs3Lc5zoBwBo71dEWH9nhurJe1mNT-I8fhIu1lQ=s88-c-k-c0x00ffffff-no-rj","author_is_uploader":false,"author_url":"https://www.youtube.com/@RedHotCivyPepper","is_favorited":false,"timestamp":1398643200,"is_pinned":false},{"id":"UgiNkhBgUtxTTngCoAEC","parent":"root","text":"complimenti a tutti bella collab!","like_count":5,"author_id":"UC8x9ZqKKvidzvQfHXlLkHVA","author":"@ZioMeso","author_thumbnail":"https://yt3.ggpht.com/fxwYe_W9wVHVM_nq-iy4HPsg3ZPh2wV_KQbThaLcS8TQVrbhYMoSf4h2g40hcvzxJ3AQmp1F=s88-c-k-c0x00ffffff-no-rj","author_is_uploader":false,"author_url":"https://www.youtube.com/@ZioMeso","is_favorited":false,"timestamp":1398643200,"is_pinned":false},{"id":"UgiM8WlYZR_83ngCoAEC","parent":"root","text":"Ahahahahah","like_count":0,"author_id":"UCyaP-qvy5QXiRCYswl0mqgg","author":"@samuelepozzi3068","author_thumbnail":"https://yt3.ggpht.com/ytc/AIdro_mDoUdx3QS_Xvqj4132hJ8pDCkwQgkYV4BYaomvG1s=s88-c-k-c0x00ffffff-no-rj","author_is_uploader":false,"author_url":"https://www.youtube.com/@samuelepozzi3068","is_favorited":false,"timestamp":1398643200,"is_pinned":false},{"id":"Ugj0BLLprC62CngCoAEC","parent":"root","text":"Il mio kebabbaro di fiducia: Dario Moccia","like_count":0,"author_id":"UCRhNVyj8Aqtx7K6qUwi5wsQ","author":"@RedHotCivyPepper","author_thumbnail":"https://yt3.ggpht.com/ytc/AIdro_mHDCGjs3Lc5zoBwBo71dEWH9nhurJe1mNT-I8fhIu1lQ=s88-c-k-c0x00ffffff-no-rj","author_is_uploader":false,"author_url":"https://www.youtube.com/@RedHotCivyPepper","is_favorited":false,"timestamp":1398643200,"is_pinned":false},{"id":"UgjUpcONT_8s_HgCoAEC","parent":"root","text":"BEST VIDEO EVER","like_count":1,"author_id":"UCNciaKtaVtvKBhz7vDb-bYg","author":"@YovanniYoni","author_thumbnail":"https://yt3.ggpht.com/8UMVS1vA3S_0B7D-e8Nvys_2WGfUMIPZXqNZ3xy7Wn_l7HX0a2Cn8yMq6e1ZDnuEMRVDAN9eYg=s88-c-k-c0x00ffffff-no-rj","author_is_uploader":false,"author_url":"https://www.youtube.com/@YovanniYoni","is_favorited":false,"timestamp":1398643200,"is_pinned":false},{"id":"UgjI4oOcaEtnTngCoAEC","parent":"root","text":"sto sborrando da ogni orifizio","like_count":2,"author_id":"UCLuU3nc2UpEndNxSY2KBI6A","author":"@CerealKillzYTP","author_thumbnail":"https://yt3.ggpht.com/IMBy5E2q3gsj3caTSTxD8OaR3LgzgyzLFDGDylT0HfRmRy5nrjNg5uxjnwhHdbTYuS_BLPIiHA=s88-c-k-c0x00ffffff-no-rj","author_is_uploader":false,"author_url":"https://www.youtube.com/@CerealKillzYTP","is_favorited":false,"timestamp":1398643200,"is_pinned":false},{"id":"UgjmKfi-MeiJengCoAEC","parent":"root","text":"Il kebabbaro di fiducia HAHHAHAHA RISI bellissimo :')","like_count":4,"author_id":"UCNgGZpIy2N3D3BrBwbZIVCg","author":"@vanillecreame","author_thumbnail":"https://yt3.ggpht.com/zNpXR8yDu4TY-OZDYYA0FzjMUvYVnaYGYfhyVsort4wTOpBVpEbeNU9W3aYfplJK7Z3G7aPcfA=s88-c-k-c0x00ffffff-no-rj","author_is_uploader":false,"author_url":"https://www.youtube.com/@vanillecreame","is_favorited":false,"timestamp":1398643200,"is_pinned":false}]