[{"id":"Ugj9bZ1WPpHchHgCoAEC","parent":"root","text":"Spettacolo! Iscritto di corsa! :)","like_count":1,"author_id":"UCFnjvnw6rA7LX_sF6MYPH3g","author":"@Barsay","author_thumbnail":"https://yt3.ggpht.com/ytc/AIdro_nx1ScI3pTbFKptpKJNMohgwaQPVMzFrupTLnkENuzv4kw=s88-c-k-c0x00ffffff-no-rj","author_is_uploader":false,"author_url":"https://www.youtube.com/@Barsay","is_favorited":false,"timestamp":1430092800,"is_pinned":false},{"id":"Ugi5_DXEXmqnNXgCoAEC","parent":"root","text":"Questo video mi ha provocato un orgasmo dietro l'altro...","like_count":2,"author_id":"UCbWHl-i9MP03sxN2ILvgmyA","author":"@Boccu03Tris","author_thumbnail":"https://yt3.ggpht.com/ytc/AIdro_lJFdumPgDjnGhTYr8uV17DfiM-IWm4vwPP9AL_8m_1TQ=s88-c-k-c0x00ffffff-no-rj","author_is_uploader":false,"author_url":"https://www.youtube.com/@Boccu03Tris","is_favorited":false,"timestamp":1430092800,"is_pinned":false},{"id":"Ugi5_DXEXmqnNXgCoAEC.7-H0Z7-7Qvz7-H88YkACWx","parent":"Ugi5_DXEXmqnNXgCoAEC","text":"è sempre un piacere dare piacere","like_count":0,"author_id":"UCm0GTp3ISFc70SiAfDRIvqQ","author":"@mijino","author_thumbnail":"https://yt3.ggpht.com/ytc/AIdro_lDsLta5dhtWVBaVdyEXhEqTMzTYwrgPnJY9jtxGeaL2Q=s88-c-k-c0x00ffffff-no-rj","author_is_uploader":true,"author_url":"https://www.youtube.com/@mijino","is_favorited":false,"timestamp":1430092800,"is_pinned":false}]