[{"id":"Ugz596WlmXCYSSSlg_p4AaABAg","parent":"root","text":"Geova si droga molto","like_count":0,"author_id":"UC3W25piJ-G6DRIBHN1kg-Gw","author":"@NikitaMateen","author_thumbnail":"https://yt3.ggpht.com/qaf5og5fvtVz2qFwkL5QWmNYJNt_exPeSTIQqMxLu8Ipqrs56u4hO3RiJX7-JxF9h6QXyZnP7SA=s88-c-k-c0x00ffffff-no-rj","author_is_uploader":false,"author_url":"https://www.youtube.com/@NikitaMateen","is_favorited":false,"timestamp":1651104000,"is_pinned":false},{"id":"UgyI3uxKLRTnwzhRMlB4AaABAg","parent":"root","text":"non puoi avere solo 20 views... ne meriti molte di più","like_count":2,"author_id":"UCo-aHoUXw-62lm5XVCPhmAg","author":"@SGRBsteo","author_thumbnail":"https://yt3.ggpht.com/ytc/AIdro_lCvzvRpKJaLXaRzIhHOWbO9J9lo5StyLjwPP3v388=s88-c-k-c0x00ffffff-no-rj","author_is_uploader":false,"author_url":"https://www.youtube.com/@SGRBsteo","is_favorited":false,"timestamp":1524873600,"is_pinned":false}]