[{"id":"UgxwbLXLCSUcK-wvCGN4AaABAg","parent":"root","text":"Fichissimo","like_count":0,"author_id":"UC71qcuJ8vkosPoHXq41qwkA","author":"@jeremylumie2303","author_thumbnail":"https://yt3.ggpht.com/ytc/AIdro_luhOYO4G5WTOze9-Zr78vX3u11ZM0qSViaJdHyZR1Yz1I=s88-c-k-c0x00ffffff-no-rj","author_is_uploader":false,"author_url":"https://www.youtube.com/@jeremylumie2303","is_favorited":false,"timestamp":1769558400,"is_pinned":false},{"id":"UgyG5Z12wLK7qAo4z254AaABAg","parent":"root","text":"Clip che hanno fatto la storia delle ytp","like_count":6,"author_id":"UCXCqi5pvQIn5TKlcfVWwQHQ","author":"@ajejebrazorf1996","author_thumbnail":"https://yt3.ggpht.com/DYZk4H9NycGU1dxLn3k0BCtF-1NDIfEkN98lJK3ksEPAzYfAEH-AbX0PxLivEifYtShfA94sw3E=s88-c-k-c0x00ffffff-no-rj","author_is_uploader":false,"author_url":"https://www.youtube.com/@ajejebrazorf1996","is_favorited":false,"timestamp":1769558400,"is_pinned":false}]