[{"id":"UghijYtXus50vngCoAEC","parent":"root","text":"Spettacolooooooooo :D","like_count":0,"author_id":"UCQ0FZpQrVNWJT8iovAMwMew","author":"@ilcarlinoytp8910","author_thumbnail":"https://yt3.ggpht.com/ytc/AIdro_nMgYeCI7O_R75YeoPIbTHFa-tzGmpRLYICIXcjPCBpoQ=s88-c-k-c0x00ffffff-no-rj","author_is_uploader":false,"author_url":"https://www.youtube.com/@ilcarlinoytp8910","is_favorited":false,"timestamp":1524873600,"is_pinned":false},{"id":"Ugh_GDSv5AFmOHgCoAEC","parent":"root","text":"Ti porto via con Giuseppe Simone xDxDxDxDxD","like_count":0,"author_id":"UC77IJu0DCaA6_sWZGAkvy2g","author":"@gfalle","author_thumbnail":"https://yt3.ggpht.com/47wJkP_1TJV4UdXXbyHljYUBFiPPxdXL1dFU9H6b_r38Iux5xrsr6JxJp9kCLEugFqA8PcxSkDQ=s88-c-k-c0x00ffffff-no-rj","author_is_uploader":false,"author_url":"https://www.youtube.com/@gfalle","is_favorited":false,"timestamp":1430179200,"is_pinned":false},{"id":"Ugiu8Oq6MHS_F3gCoAEC","parent":"root","text":"tu sei un geniooooooooo","like_count":0,"author_id":"UCmzOjm6_V2Kyb-lvAOvhTow","author":"@marianalaukova7467","author_thumbnail":"https://yt3.ggpht.com/ytc/AIdro_mIYp_PB4T1evtVDw3-TLmAWH-tIKxDsVP5t_yWAwLYeK8=s88-c-k-c0x00ffffff-no-rj","author_is_uploader":false,"author_url":"https://www.youtube.com/@marianalaukova7467","is_favorited":false,"timestamp":1430179200,"is_pinned":false}]